{
  "open_nodes": [
    {
      "id": "char_emma",
      "label": "Emma",
      "node_type": "Character"
    },
    {
      "id": "char_walter_scott",
      "label": "Walter Scott",
      "node_type": "Character"
    },
    {
      "id": "char_mary_stuart",
      "label": "Mary Stuart",
      "node_type": "Character"
    },
    {
      "id": "char_joan_of_arc",
      "label": "Joan of Arc",
      "node_type": "Character"
    },
    {
      "id": "char_heloise",
      "label": "Heloise",
      "node_type": "Character"
    },
    {
      "id": "char_agnes_sorel",
      "label": "Agnes Sorel",
      "node_type": "Character"
    },
    {
      "id": "char_charles",
      "label": "Charles",
      "node_type": "Character"
    },
    {
      "id": "char_charles_mother",
      "label": "Madame Bovary senior",
      "node_type": "Character"
    },
    {
      "id": "char_emma_mother",
      "label": "Emma's mother",
      "node_type": "Character"
    },
    {
      "id": "evt_reading_keepsakes",
      "label": "Emma reading keepsakes in the dormitory",
      "node_type": "Event"
    },
    {
      "id": "evt_mother_death",
      "label": "Emma's mother dies",
      "node_type": "Event"
    },
    {
      "id": "evt_leaving_school",
      "label": "Emma leaves the convent school",
      "node_type": "Event"
    },
    {
      "id": "evt_charles_first_visit",
      "label": "Charles comes to the Bertaux for the first time",
      "node_type": "Event"
    },
    {
      "id": "evt_marriage",
      "label": "Emma and Charles marry",
      "node_type": "Event"
    },
    {
      "id": "evt_honeymoon",
      "label": "The honeymoon period",
      "node_type": "Event"
    },
    {
      "id": "evt_charles_mother_visits",
      "label": "Madame Bovary senior visits and criticizes Emma",
      "node_type": "Event"
    },
    {
      "id": "evt_emma_walks_alone",
      "label": "Emma walks alone to the pavilion near Banneville",
      "node_type": "Event"
    },
    {
      "id": "loc_convent",
      "label": "The convent school",
      "node_type": "Location"
    },
    {
      "id": "loc_dormitory",
      "label": "The dormitory",
      "node_type": "Location"
    },
    {
      "id": "loc_music_class",
      "label": "The music class",
      "node_type": "Location"
    },
    {
      "id": "loc_bertaux",
      "label": "The Bertaux",
      "node_type": "Location"
    },
    {
      "id": "loc_home",
      "label": "Emma and Charles's home",
      "node_type": "Location"
    },
    {
      "id": "loc_garden",
      "label": "The garden",
      "node_type": "Location"
    },
    {
      "id": "loc_pavilion",
      "label": "The deserted pavilion near Banneville",
      "node_type": "Location"
    },
    {
      "id": "loc_rouen",
      "label": "Rouen",
      "node_type": "Location"
    }
  ],
  "closed_nodes": [
    {
      "id": "role_emma_soggetto",
      "label": "SOGGETTO_EROE",
      "node_type": "Role"
    },
    {
      "id": "role_charles_opponente",
      "label": "OPPONENTE_ANTAGONISTA",
      "node_type": "Role"
    },
    {
      "id": "role_charles_mother_opponente",
      "label": "OPPONENTE_ANTAGONISTA",
      "node_type": "Role"
    },
    {
      "id": "evt_type_esposizione",
      "label": "ESPOSIZIONE",
      "node_type": "EventType"
    },
    {
      "id": "evt_type_predicamento",
      "label": "PREDICAMENTO",
      "node_type": "EventType"
    },
    {
      "id": "evt_type_cambiamento",
      "label": "CAMBIAMENTO_DI_STATO",
      "node_type": "EventType"
    },
    {
      "id": "evt_type_rivelazione",
      "label": "RIVELAZIONE_SCOPERTA",
      "node_type": "EventType"
    },
    {
      "id": "loc_type_chiuso",
      "label": "AL_CHIUSO",
      "node_type": "LocationType"
    },
    {
      "id": "loc_type_aperto",
      "label": "ALL_APERTO",
      "node_type": "LocationType"
    },
    {
      "id": "loc_type_affettivo",
      "label": "SPAZIO_AFFETTIVO",
      "node_type": "LocationType"
    }
  ],
  "relations": [
    {
      "source_id": "char_emma",
      "edge_label": "COME",
      "target_open_id": null,
      "target_closed_value": "SOGGETTO_EROE"
    },
    {
      "source_id": "char_charles",
      "edge_label": "COME",
      "target_open_id": null,
      "target_closed_value": "OPPONENTE_ANTAGONISTA"
    },
    {
      "source_id": "char_charles_mother",
      "edge_label": "COME",
      "target_open_id": null,
      "target_closed_value": "OPPONENTE_ANTAGONISTA"
    },
    {
      "source_id": "evt_reading_keepsakes",
      "edge_label": "COME",
      "target_open_id": null,
      "target_closed_value": "ESPOSIZIONE"
    },
    {
      "source_id": "evt_mother_death",
      "edge_label": "COME",
      "target_open_id": null,
      "target_closed_value": "CAMBIAMENTO_DI_STATO"
    },
    {
      "source_id": "evt_leaving_school",
      "edge_label": "COME",
      "target_open_id": null,
      "target_closed_value": "CAMBIAMENTO_DI_STATO"
    },
    {
      "source_id": "evt_charles_first_visit",
      "edge_label": "COME",
      "target_open_id": null,
      "target_closed_value": "RIVELAZIONE_SCOPERTA"
    },
    {
      "source_id": "evt_marriage",
      "edge_label": "COME",
      "target_open_id": null,
      "target_closed_value": "CAMBIAMENTO_DI_STATO"
    },
    {
      "source_id": "evt_honeymoon",
      "edge_label": "COME",
      "target_open_id": null,
      "target_closed_value": "PREDICAMENTO"
    },
    {
      "source_id": "evt_charles_mother_visits",
      "edge_label": "COME",
      "target_open_id": null,
      "target_closed_value": "PREDICAMENTO"
    },
    {
      "source_id": "evt_emma_walks_alone",
      "edge_label": "COME",
      "target_open_id": null,
      "target_closed_value": "RIVELAZIONE_SCOPERTA"
    },
    {
      "source_id": "loc_convent",
      "edge_label": "COME",
      "target_open_id": null,
      "target_closed_value": "AL_CHIUSO"
    },
    {
      "source_id": "loc_dormitory",
      "edge_label": "COME",
      "target_open_id": null,
      "target_closed_value": "AL_CHIUSO"
    },
    {
      "source_id": "loc_home",
      "edge_label": "COME",
      "target_open_id": null,
      "target_closed_value": "SPAZIO_AFFETTIVO"
    },
    {
      "source_id": "loc_garden",
      "edge_label": "COME",
      "target_open_id": null,
      "target_closed_value": "ALL_APERTO"
    },
    {
      "source_id": "loc_pavilion",
      "edge_label": "COME",
      "target_open_id": null,
      "target_closed_value": "ALL_APERTO"
    },
    {
      "source_id": "char_emma",
      "edge_label": "PARTECIPA_COME_SOGGETTO",
      "target_open_id": "evt_reading_keepsakes",
      "target_closed_value": null
    },
    {
      "source_id": "char_emma",
      "edge_label": "PARTECIPA_COME_SOGGETTO",
      "target_open_id": "evt_mother_death",
      "target_closed_value": null
    },
    {
      "source_id": "char_emma_mother",
      "edge_label": "PARTECIPA_COME_OGGETTO_BERSAGLIO",
      "target_open_id": "evt_mother_death",
      "target_closed_value": null
    },
    {
      "source_id": "char_emma",
      "edge_label": "PARTECIPA_COME_SOGGETTO",
      "target_open_id": "evt_leaving_school",
      "target_closed_value": null
    },
    {
      "source_id": "char_emma",
      "edge_label": "PARTECIPA_COME_SOGGETTO",
      "target_open_id": "evt_charles_first_visit",
      "target_closed_value": null
    },
    {
      "source_id": "char_charles",
      "edge_label": "PARTECIPA_COME_SOGGETTO",
      "target_open_id": "evt_charles_first_visit",
      "target_closed_value": null
    },
    {
      "source_id": "char_emma",
      "edge_label": "PARTECIPA_COME_SOGGETTO",
      "target_open_id": "evt_marriage",
      "target_closed_value": null
    },
    {
      "source_id": "char_charles",
      "edge_label": "PARTECIPA_COME_SOGGETTO",
      "target_open_id": "evt_marriage",
      "target_closed_value": null
    },
    {
      "source_id": "char_emma",
      "edge_label": "PARTECIPA_COME_SOGGETTO",
      "target_open_id": "evt_honeymoon",
      "target_closed_value": null
    },
    {
      "source_id": "char_charles",
      "edge_label": "PARTECIPA_COME_SOGGETTO",
      "target_open_id": "evt_honeymoon",
      "target_closed_value": null
    },
    {
      "source_id": "char_charles_mother",
      "edge_label": "PARTECIPA_COME_SOGGETTO",
      "target_open_id": "evt_charles_mother_visits",
      "target_closed_value": null
    },
    {
      "source_id": "char_emma",
      "edge_label": "PARTECIPA_COME_OGGETTO_BERSAGLIO",
      "target_open_id": "evt_charles_mother_visits",
      "target_closed_value": null
    },
    {
      "source_id": "char_charles",
      "edge_label": "PARTECIPA_COME_SOGGETTO",
      "target_open_id": "evt_charles_mother_visits",
      "target_closed_value": null
    },
    {
      "source_id": "char_emma",
      "edge_label": "PARTECIPA_COME_SOGGETTO",
      "target_open_id": "evt_emma_walks_alone",
      "target_closed_value": null
    },
    {
      "source_id": "evt_reading_keepsakes",
      "edge_label": "AVVIENE_IN",
      "target_open_id": "loc_dormitory",
      "target_closed_value": null
    },
    {
      "source_id": "evt_leaving_school",
      "edge_label": "AVVIENE_IN",
      "target_open_id": "loc_convent",
      "target_closed_value": null
    },
    {
      "source_id": "evt_charles_first_visit",
      "edge_label": "AVVIENE_IN",
      "target_open_id": "loc_bertaux",
      "target_closed_value": null
    },
    {
      "source_id": "evt_marriage",
      "edge_label": "AVVIENE_IN",
      "target_open_id": "loc_home",
      "target_closed_value": null
    },
    {
      "source_id": "evt_honeymoon",
      "edge_label": "AVVIENE_IN",
      "target_open_id": "loc_home",
      "target_closed_value": null
    },
    {
      "source_id": "evt_charles_mother_visits",
      "edge_label": "AVVIENE_IN",
      "target_open_id": "loc_home",
      "target_closed_value": null
    },
    {
      "source_id": "evt_emma_walks_alone",
      "edge_label": "AVVIENE_IN",
      "target_open_id": "loc_pavilion",
      "target_closed_value": null
    },
    {
      "source_id": "evt_reading_keepsakes",
      "edge_label": "AVVIENE_DOPO",
      "target_open_id": "evt_mother_death",
      "target_closed_value": null
    },
    {
      "source_id": "evt_leaving_school",
      "edge_label": "AVVIENE_DOPO",
      "target_open_id": "evt_mother_death",
      "target_closed_value": null
    },
    {
      "source_id": "evt_charles_first_visit",
      "edge_label": "AVVIENE_DOPO",
      "target_open_id": "evt_leaving_school",
      "target_closed_value": null
    },
    {
      "source_id": "evt_marriage",
      "edge_label": "AVVIENE_DOPO",
      "target_open_id": "evt_charles_first_visit",
      "target_closed_value": null
    },
    {
      "source_id": "evt_honeymoon",
      "edge_label": "AVVIENE_DOPO",
      "target_open_id": "evt_marriage",
      "target_closed_value": null
    },
    {
      "source_id": "evt_charles_mother_visits",
      "edge_label": "AVVIENE_DOPO",
      "target_open_id": "evt_honeymoon",
      "target_closed_value": null
    },
    {
      "source_id": "evt_emma_walks_alone",
      "edge_label": "AVVIENE_DOPO",
      "target_open_id": "evt_charles_mother_visits",
      "target_closed_value": null
    },
    {
      "source_id": "char_walter_scott",
      "edge_label": "PARTECIPA_COME_DONATORE",
      "target_open_id": "evt_reading_keepsakes",
      "target_closed_value": null
    },
    {
      "source_id": "char_mary_stuart",
      "edge_label": "PARTECIPA_COME_SPETTATORE_NEUTRALE",
      "target_open_id": "evt_reading_keepsakes",
      "target_closed_value": null
    },
    {
      "source_id": "char_joan_of_arc",
      "edge_label": "PARTECIPA_COME_SPETTATORE_NEUTRALE",
      "target_open_id": "evt_reading_keepsakes",
      "target_closed_value": null
    },
    {
      "source_id": "char_heloise",
      "edge_label": "PARTECIPA_COME_SPETTATORE_NEUTRALE",
      "target_open_id": "evt_reading_keepsakes",
      "target_closed_value": null
    },
    {
      "source_id": "char_agnes_sorel",
      "edge_label": "PARTECIPA_COME_SPETTATORE_NEUTRALE",
      "target_open_id": "evt_reading_keepsakes",
      "target_closed_value": null
    }
  ]
}